{
  "db_name": "PostgreSQL",
  "query": "SELECT amount, payment_request FROM pending_invoices WHERE key = $1",
  "describe": {
    "columns": [
      {
        "ordinal": 0,
        "name": "amount",
        "type_info": "Int8"
      },
      {
        "ordinal": 1,
        "name": "payment_request",
        "type_info": "Text"
      }
    ],
    "parameters": {
      "Left": [
        "Text"
      ]
    },
    "nullable": [
      false,
      false
    ]
  },
  "hash": "9db8c4f6f5c71b2a0e4476429931112334053812decdbc7869404a7806d33856"
}
